facebook_business_mcp/__init__.py
facebook_business_mcp/__main__.py
facebook_business_mcp/config.py
facebook_business_mcp/utils.py
facebook_business_mcp/generated/models/__init__.py
facebook_business_mcp/generated/models/generated_models.py
facebook_business_mcp/servers/higher_order.py
facebook_business_mcp/servers/ad/__init__.py
facebook_business_mcp/servers/ad/crud.py
facebook_business_mcp/servers/ad/operations.py
facebook_business_mcp/servers/ad/server.py
facebook_business_mcp/servers/adaccount/__init__.py
facebook_business_mcp/servers/adaccount/ad_sets.py
facebook_business_mcp/servers/adaccount/crud.py
facebook_business_mcp/servers/adaccount/server.py
facebook_business_mcp/servers/adcreative/__init__.py
facebook_business_mcp/servers/adcreative/crud.py
facebook_business_mcp/servers/adcreative/helpers.py
facebook_business_mcp/servers/adcreative/operations.py
facebook_business_mcp/servers/adcreative/server.py
facebook_business_mcp/servers/adset/__init__.py
facebook_business_mcp/servers/adset/ads.py
facebook_business_mcp/servers/adset/crud.py
facebook_business_mcp/servers/adset/operations.py
facebook_business_mcp/servers/adset/server.py
facebook_business_mcp/servers/campaign/__init__.py
facebook_business_mcp/servers/campaign/ad_sets.py
facebook_business_mcp/servers/campaign/ads.py
facebook_business_mcp/servers/campaign/copies.py
facebook_business_mcp/servers/campaign/crud.py
facebook_business_mcp/servers/campaign/server.py
facebook_business_mcp/servers/insights/__init__.py
facebook_business_mcp/servers/insights/operations.py
facebook_business_mcp/servers/insights/server.py
facebook_business_mcp/servers/insights/specialized.py
facebook_business_mcp-0.0.9.dev2.dist-info/METADATA
facebook_business_mcp-0.0.9.dev2.dist-info/WHEEL
facebook_business_mcp-0.0.9.dev2.dist-info/entry_points.txt
facebook_business_mcp-0.0.9.dev2.dist-info/licenses/LICENSE
facebook_business_mcp-0.0.9.dev2.dist-info/RECORD
