Metadata-Version: 2.4
Name: facebook-business-mcp
Version: 0.0.9.dev2
Summary: unofficial MCP server implementation for Facebook Business API
Project-URL: Repository, https://github.com/promobase/facebook-business-mcp
Author-email: PromoBase <li.ruize09@gmail.com>
License-Expression: MIT
License-File: LICENSE
Classifier: Development Status :: 4 - Beta
Classifier: Intended Audience :: Developers
Classifier: Operating System :: OS Independent
Classifier: Programming Language :: Python
Classifier: Programming Language :: Python :: 3
Classifier: Programming Language :: Python :: 3.11
Classifier: Programming Language :: Python :: 3.12
Classifier: Programming Language :: Python :: 3.13
Classifier: Typing :: Typed
Requires-Python: <4.0,>=3.11
Requires-Dist: facebook-business>=23.0.0
Requires-Dist: fastmcp>=2.9.2
